LICENSE.md
MANIFEST.in
README.md
setup.cfg
setup.py
bin/checkCompletion
bin/kronosversion.py
bin/runkronos.sh
python/kronos/__init__.py
python/kronos/app.py
python/kronos/dbConvenience.py
python/kronos/designCompletion.py
python/kronos/jinja_filters.py
python/kronos/scheduler.py
python/kronos/site.py
python/kronos/vizWindow.py
python/kronos/controllers/__init__.py
python/kronos/controllers/dbEndPoints.py
python/kronos/controllers/designDetail.py
python/kronos/controllers/designQuery.py
python/kronos/controllers/fieldDetail.py
python/kronos/controllers/fieldQuery.py
python/kronos/controllers/fieldViz.py
python/kronos/controllers/index.py
python/kronos/controllers/lookAhead.py
python/kronos/controllers/planObserving.py
python/sdss_kronos.egg-info/PKG-INFO
python/sdss_kronos.egg-info/SOURCES.txt
python/sdss_kronos.egg-info/dependency_links.txt
python/sdss_kronos.egg-info/not-zip-safe
python/sdss_kronos.egg-info/requires.txt
python/sdss_kronos.egg-info/top_level.txt