Metadata-Version: 2.1
Name: sdss-kronos
Version: 1.0.0
Summary: robot scheduling app for SDSS V
Home-page: https://github.com/sdss/kronos
Author: John Donor
Author-email: j.donor@tcu.edu
License: BSD 3-Clause License
Project-URL: Repository, https://github.com/sdss/kronos
Project-URL: Documentation, https://sdss-kronos.readthedocs.org
Keywords: astronomy,software
Platform: UNKNOWN
Classifier: Intended Audience :: Science/Research
Classifier: Natural Language :: English
Classifier: Operating System :: OS Independent
Classifier: Programming Language :: Python
Classifier: Programming Language :: Python :: 3.7
Classifier: Programming Language :: Python :: 3.8
Classifier: Topic :: Documentation :: Sphinx
Classifier: Topic :: Software Development :: Libraries :: Python Modules
Requires-Python: >=3.7
Provides-Extra: dev
Provides-Extra: docs
